nakdimon/Nakdimon.h5
nakdimon/__init__.py
nakdimon/__main__.py
nakdimon/ablations.py
nakdimon/config.py
nakdimon/dataset.py
nakdimon/external_apis.py
nakdimon/hebrew.py
nakdimon/metrics.py
nakdimon/partial_modern.py
nakdimon/predict.py
nakdimon/pretrain.py
nakdimon/run_test.py
nakdimon/schedulers.py
nakdimon/server.py
nakdimon/table_maker.py
nakdimon/train.py
nakdimon/transformer.py
nakdimon/utils.py
nakdimon-0.1.2.dist-info/LICENSE
nakdimon-0.1.2.dist-info/METADATA
nakdimon-0.1.2.dist-info/WHEEL
nakdimon-0.1.2.dist-info/entry_points.txt
nakdimon-0.1.2.dist-info/top_level.txt
nakdimon-0.1.2.dist-info/RECORD
