Metadata-Version: 2.1
Name: nakdimon
Version: 0.1.2
Summary: Diacritic restoration for Hebrew
Author-email: Elazar Gershuni <elazarg@gmail.com>
License: Copyright 2022, Elazar Gershuni
Project-URL: Homepage, https://github.com/elazarg/nakdimon
Project-URL: Bug Tracker, https://github.com/elazarg/nakdimon/issues
Classifier: Programming Language :: Python :: 3
Classifier: License :: OSI Approved :: MIT License
Classifier: Operating System :: OS Independent
Requires-Python: >=3.11
License-File: LICENSE
Requires-Dist: numpy ==1.26.2
Requires-Dist: requests ==2.32.3
Requires-Dist: requests-oauthlib ==1.3.1
Requires-Dist: Flask ==2.2.5
Requires-Dist: keras ==2.15.0
Requires-Dist: tensorflowjs ==4.20.0
Requires-Dist: tensorflow ==2.15.0
Requires-Dist: wandb ==0.17.0
Requires-Dist: prettytable ==3.6.0
